{
	"version": "6",
	"dialect": "sqlite",
	"id": "1df727ed-95fd-4b5e-9f61-07b802521969",
	"prevId": "00000000-0000-0000-0000-000000000000",
	"tables": {
		"signup_sessions": {
			"name": "signup_sessions",
			"columns": {
				"id": {
					"name": "id",
					"type": "text",
					"primaryKey": true,
					"notNull": true,
					"autoincrement": false
				},
				"email": {
					"name": "email",
					"type": "text",
					"primaryKey": false,
					"notNull": true,
					"autoincrement": false
				},
				"token_hash": {
					"name": "token_hash",
					"type": "text",
					"primaryKey": false,
					"notNull": true,
					"autoincrement": false
				},
				"expires_at": {
					"name": "expires_at",
					"type": "integer",
					"primaryKey": false,
					"notNull": true,
					"autoincrement": false
				}
			},
			"indexes": {
				"signup_sessions_token_hash_unique": {
					"name": "signup_sessions_token_hash_unique",
					"columns": ["token_hash"],
					"isUnique": true
				}
			},
			"foreignKeys": {},
			"compositePrimaryKeys": {},
			"uniqueConstraints": {},
			"checkConstraints": {}
		},
		"users": {
			"name": "users",
			"columns": {
				"id": {
					"name": "id",
					"type": "text",
					"primaryKey": true,
					"notNull": true,
					"autoincrement": false
				},
				"email": {
					"name": "email",
					"type": "text",
					"primaryKey": false,
					"notNull": true,
					"autoincrement": false
				},
				"salt": {
					"name": "salt",
					"type": "text",
					"primaryKey": false,
					"notNull": false,
					"autoincrement": false
				},
				"password_hash": {
					"name": "password_hash",
					"type": "text",
					"primaryKey": false,
					"notNull": false,
					"autoincrement": false
				},
				"google_id": {
					"name": "google_id",
					"type": "text",
					"primaryKey": false,
					"notNull": false,
					"autoincrement": false
				},
				"created_at": {
					"name": "created_at",
					"type": "integer",
					"primaryKey": false,
					"notNull": true,
					"autoincrement": false,
					"default": "(unixepoch())"
				}
			},
			"indexes": {
				"users_email_unique": {
					"name": "users_email_unique",
					"columns": ["email"],
					"isUnique": true
				},
				"users_google_id_unique": {
					"name": "users_google_id_unique",
					"columns": ["google_id"],
					"isUnique": true
				}
			},
			"foreignKeys": {},
			"compositePrimaryKeys": {},
			"uniqueConstraints": {},
			"checkConstraints": {}
		}
	},
	"views": {},
	"enums": {},
	"_meta": {
		"schemas": {},
		"tables": {},
		"columns": {}
	},
	"internal": {
		"indexes": {}
	}
}
